sdram_controller.v
/**
 * simple controller for ISSI IS42S16160G-7 SDRAM found in De0 Nano
 *  16Mbit x 16 data bit bus (32 megabytes)
 *  Default options
 *    133Mhz
 *    CAS 3
 *
 *  Very simple host interface
 *     * No burst support
 *     * haddr - address for reading and wriging 16 bits of data
 *     * data_input - data for writing, latched in when wr_enable is highz0
 *     * data_output - data for reading, comes available sometime
 *       *few clocks* after rd_enable and address is presented on bus
 *     * rst_n - start init ram process
 *     * rd_enable - read enable, on clk posedge haddr will be latched in,
 *       after *few clocks* data will be available on the data_output port
 *     * wr_enable - write enable, on clk posedge haddr and data_input will
 *       be latched in, after *few clocks* data will be written to sdram
 *
 * Theory
 *  This simple host interface has a busy signal to tell you when you are
 *  not able to issue commands.
 */
//stffrdhrn
module sdram_controller (
    /* HOST INTERFACE */
    wr_addr,
    wr_data,
    wr_enable,

    rd_addr,
    rd_data,
    rd_ready,
    rd_enable,

    busy, rst_n, clk,

    /* SDRAM SIDE */
    addr, bank_addr, data, clock_enable, cs_n, ras_n, cas_n, we_n,
    data_mask_low, data_mask_high
);

/* Internal Parameters */
parameter ROW_WIDTH = 12;
parameter COL_WIDTH = 8;
parameter BANK_WIDTH = 2;

parameter SDRADDR_WIDTH = ROW_WIDTH > COL_WIDTH ? ROW_WIDTH : COL_WIDTH;
parameter HADDR_WIDTH = BANK_WIDTH + ROW_WIDTH + COL_WIDTH;

parameter CLK_FREQUENCY = 100;  // Mhz
parameter REFRESH_TIME = 64;   // ms     (how often we need to refresh)
parameter REFRESH_COUNT = 4096; // cycles (how many refreshes required per refresh time)

// clk / refresh =  clk / sec
//                , sec / refbatch
//                , ref / refbatch
localparam CYCLES_BETWEEN_REFRESH = ( CLK_FREQUENCY
                                      * 1_000
                                      * REFRESH_TIME
                                    ) / REFRESH_COUNT;

// STATES - State
localparam IDLE      = 5'b00000;

localparam INIT_NOP1 = 5'b01000,
           INIT_PRE1 = 5'b01001,
           INIT_NOP1_1=5'b00101,
           INIT_REF1 = 5'b01010,
           INIT_NOP2 = 5'b01011,
           INIT_REF2 = 5'b01100,
           INIT_NOP3 = 5'b01101,
           INIT_LOAD = 5'b01110,
           INIT_NOP4 = 5'b01111;

localparam REF_PRE  =  5'b00001,
           REF_NOP1 =  5'b00010,
           REF_REF  =  5'b00011,
           REF_NOP2 =  5'b00100;

localparam READ_ACT  = 5'b10000,
           READ_NOP1 = 5'b10001,
           READ_CAS  = 5'b10010,
           READ_NOP2 = 5'b10011,
           READ_READ = 5'b10100;

localparam WRIT_ACT  = 5'b11000,
           WRIT_NOP1 = 5'b11001,
           WRIT_CAS  = 5'b11010,
           WRIT_NOP2 = 5'b11011;

// Commands              CCRCWBBA
//                       ESSSE100
localparam CMD_PALL = 8'b10010001,
           CMD_REF  = 8'b10001000,
           CMD_NOP  = 8'b10111000,
           CMD_MRS  = 8'b1000000x,
           CMD_BACT = 8'b10011xxx,
           CMD_READ = 8'b10101xx1,
           CMD_WRIT = 8'b10100xx1;

/* Interface Definition */
/* HOST INTERFACE */
input  [HADDR_WIDTH-1:0]   wr_addr;
input  [15:0]              wr_data;
input                      wr_enable;

input  [HADDR_WIDTH-1:0]   rd_addr;
output [15:0]              rd_data;
input                      rd_enable;
output                     rd_ready;

output                     busy;
input                      rst_n;
input                      clk;

/* SDRAM SIDE */
output [SDRADDR_WIDTH-1:0] addr;
output [BANK_WIDTH-1:0]    bank_addr;
inout  [15:0]              data;
output                     clock_enable;
output                     cs_n;
output                     ras_n;
output                     cas_n;
output                     we_n;
output                     data_mask_low;
output                     data_mask_high;

/* I/O Registers */

reg  [HADDR_WIDTH-1:0]   haddr_r;
reg  [15:0]              wr_data_r;
reg  [15:0]              rd_data_r;
reg                      busy;
reg                      data_mask_low_r;
reg                      data_mask_high_r;
reg [SDRADDR_WIDTH-1:0]  addr_r;
reg [BANK_WIDTH-1:0]     bank_addr_r;
reg                      rd_ready_r;

wire [15:0]              data_output;
wire                     data_mask_low, data_mask_high;

assign data_mask_high = data_mask_high_r;
assign data_mask_low  = data_mask_low_r;
assign rd_data        = rd_data_r;

/* Internal Wiring */
reg [3:0] state_cnt;
reg [9:0] refresh_cnt;

reg [7:0] command;
reg [4:0] state;

// TODO output addr[6:4] when programming mode register

reg [7:0] command_nxt;
reg [3:0] state_cnt_nxt;
reg [4:0] next;

assign {clock_enable, cs_n, ras_n, cas_n, we_n} = command[7:3];
// state[4] will be set if mode is read/write
assign bank_addr      = (state[4]) ? bank_addr_r : command[2:1];
assign addr           = (state[4] | state == INIT_LOAD) ? addr_r : { {SDRADDR_WIDTH-11{1'b0}}, command[0], 10'd0 };

assign data = (state == WRIT_CAS) ? wr_data_r : 16'bz;
assign rd_ready = rd_ready_r;

// HOST INTERFACE
// all registered on posedge
always @ (posedge clk)
  if (~rst_n)
    begin
    state <= INIT_NOP1;
    command <= CMD_NOP;
    state_cnt <= 4'hf;

    haddr_r <= {HADDR_WIDTH{1'b0}};
    wr_data_r <= 16'b0;
    rd_data_r <= 16'b0;
    busy <= 1'b0;
    end
  else
    begin

    state <= next;
    command <= command_nxt;

    if (!state_cnt)
      state_cnt <= state_cnt_nxt;
    else
      state_cnt <= state_cnt - 1'b1;

    if (wr_enable)
      wr_data_r <= wr_data;

    if (state == READ_READ)
      begin
      rd_data_r <= data;
      rd_ready_r <= 1'b1;
      end
    else
      rd_ready_r <= 1'b0;

    busy <= state[4];

    if (rd_enable)
      haddr_r <= rd_addr;
    else if (wr_enable)
      haddr_r <= wr_addr;

    end

// Handle refresh counter
always @ (posedge clk)
 if (~rst_n)
   refresh_cnt <= 10'b0;
 else
   if (state == REF_NOP2)
     refresh_cnt <= 10'b0;
   else
     refresh_cnt <= refresh_cnt + 1'b1;


/* Handle logic for sending addresses to SDRAM based on current state*/
always @*
begin
    if (state[4])
      {data_mask_low_r, data_mask_high_r} = 2'b00;
    else
      {data_mask_low_r, data_mask_high_r} = 2'b11;

   bank_addr_r = 2'b00;
   addr_r = {SDRADDR_WIDTH{1'b0}};

   if (state == READ_ACT | state == WRIT_ACT)
     begin
     bank_addr_r = haddr_r[HADDR_WIDTH-1:HADDR_WIDTH-(BANK_WIDTH)];
     addr_r = haddr_r[HADDR_WIDTH-(BANK_WIDTH+1):HADDR_WIDTH-(BANK_WIDTH+ROW_WIDTH)];
     end
   else if (state == READ_CAS | state == WRIT_CAS)
     begin
     // Send Column Address
     // Set bank to bank to precharge
     bank_addr_r = haddr_r[HADDR_WIDTH-1:HADDR_WIDTH-(BANK_WIDTH)];

     // Examples for math
     //               BANK  ROW    COL
     // HADDR_WIDTH   2 +   13 +   9   = 24
     // SDRADDR_WIDTH 13

     // Set CAS address to:
     //   0s,
     //   1 (A10 is always for auto precharge),
     //   0s,
     //   column address
     addr_r = {
               {SDRADDR_WIDTH-(11){1'b0}},
               1'b1,                       /* A10 */
               {10-COL_WIDTH{1'b0}},
               haddr_r[COL_WIDTH-1:0]
              };
     end
   else if (state == INIT_LOAD)
     begin
     // Program mode register during load cycle
     //                                       B  C  SB
     //                                       R  A  EUR
     //                                       S  S-3Q ST
     //                                       T  654L210
     addr_r = {{SDRADDR_WIDTH-10{1'b0}}, 10'b1000110000};
     end
end

// Next state logic
always @*
begin
   state_cnt_nxt = 4'd0;
   command_nxt = CMD_NOP;
   if (state == IDLE)
        // Monitor for refresh or hold
        if (refresh_cnt >= CYCLES_BETWEEN_REFRESH)
          begin
          next = REF_PRE;
          command_nxt = CMD_PALL;
          end
        else if (rd_enable)
          begin
          next = READ_ACT;
          command_nxt = CMD_BACT;
          end
        else if (wr_enable)
          begin
          next = WRIT_ACT;
          command_nxt = CMD_BACT;
          end
        else
          begin
          // HOLD
          next = IDLE;
          end
    else
      if (!state_cnt)
        case (state)
          // INIT ENGINE
          INIT_NOP1:
            begin
            next = INIT_PRE1;
            command_nxt = CMD_PALL;
            end
          INIT_PRE1:
            begin
            next = INIT_NOP1_1;
            end
          INIT_NOP1_1:
            begin
            next = INIT_REF1;
            command_nxt = CMD_REF;
            end
          INIT_REF1:
            begin
            next = INIT_NOP2;
            state_cnt_nxt = 4'd7;
            end
          INIT_NOP2:
            begin
            next = INIT_REF2;
            command_nxt = CMD_REF;
            end
          INIT_REF2:
            begin
            next = INIT_NOP3;
            state_cnt_nxt = 4'd7;
            end
          INIT_NOP3:
            begin
            next = INIT_LOAD;
            command_nxt = CMD_MRS;
            end
          INIT_LOAD:
            begin
            next = INIT_NOP4;
            state_cnt_nxt = 4'd1;
            end
          // INIT_NOP4: default - IDLE

          // REFRESH
          REF_PRE:
            begin
            next = REF_NOP1;
            end
          REF_NOP1:
            begin
            next = REF_REF;
            command_nxt = CMD_REF;
            end
          REF_REF:
            begin
            next = REF_NOP2;
            state_cnt_nxt = 4'd7;
            end
          // REF_NOP2: default - IDLE

          // WRITE
          WRIT_ACT:
            begin
            next = WRIT_NOP1;
            state_cnt_nxt = 4'd1;
            end
          WRIT_NOP1:
            begin
            next = WRIT_CAS;
            command_nxt = CMD_WRIT;
            end
          WRIT_CAS:
            begin
            next = WRIT_NOP2;
            state_cnt_nxt = 4'd1;
            end
          // WRIT_NOP2: default - IDLE

          // READ
          READ_ACT:
            begin
            next = READ_NOP1;
            state_cnt_nxt = 4'd1;
            end
          READ_NOP1:
            begin
            next = READ_CAS;
            command_nxt = CMD_READ;
            end
          READ_CAS:
            begin
            next = READ_NOP2;
            state_cnt_nxt = 4'd1;
            end
          READ_NOP2:
            begin
            next = READ_READ;
            end
          // READ_READ: default - IDLE

          default:
            begin
            next = IDLE;
            end
          endcase
      else
        begin
        // Counter Not Reached - HOLD
        next = state;
        command_nxt = command;
        end
end

endmodule

sdram_controller_tb.v
/**
 * Testbench for sdram_controller modules, simulates:
 *  - Iinit
 *  - Write
 *  - Read
 */
 `timescale 1 ps/ 1 ps
module sdram_controller_tb();

    //vlog_tb_utils vlog_tb_utils0();

    /* HOST CONTROLLS */
    reg [21:0]  haddr;
    reg [15:0]  data_input;
    wire [15:0] data_output;
    wire busy; 
    reg rd_enable, wr_enable, rst_n, clk;

    /* SDRAM SIDE */
    wire [11:0] addr;
    wire [1:0] bank_addr;
    wire [15:0] data; 
    wire clock_enable, cs_n, ras_n, cas_n, we_n, data_mask_low, data_mask_high;

    reg [15:0] data_r;

    assign data = data_r;


    initial 
    begin
        haddr = 22'd0;
        data_input = 16'd0;
        rd_enable = 1'b0;
        wr_enable = 1'b0;
        rst_n = 1'b1;
        clk = 1'b0;
        data_r = 16'hzzzz;
    end

    always
        #1 clk <= ~clk;
      
    initial
    begin
      #3 rst_n = 1'b0;
      #3 rst_n = 1'b1;
      
      #120 haddr = 22'hfedbed;
      data_input = 16'd3333;
      
      #3 wr_enable = 1'b1;
      #6 wr_enable = 1'b0;
      haddr = 22'd0;
      data_input = 16'd0;  
      
      #120 haddr = 22'hbedfed;
      #3 rd_enable = 1'b1;
      #6 rd_enable = 1'b0;
      haddr = 22'd0;
      
      #8 data_r = 16'hbbbb;
      #2 data_r = 16'hzzzz;
      
      #5000 $finish;
    end

    initial 
    begin
        $dumpfile("output_sdram_test.vcd");
        $dumpvars; //(2,stimulus);
    
        //reset =1;
        //#2 reset = 0;
        //#2 reset =1;
    end


sdram_controller sdram_controlleri (
    /* HOST INTERFACE */
    .wr_addr(haddr), 
    .wr_data(data_input),
    .rd_addr(haddr),
    .rd_data(data_output),
    .busy(busy), .rd_enable(rd_enable), .wr_enable(wr_enable), .rst_n(rst_n), .clk(clk),

    /* SDRAM SIDE */
    .addr(addr), .bank_addr(bank_addr), .data(data), .clock_enable(clock_enable), .cs_n(cs_n), .ras_n(ras_n), .cas_n(cas_n), .we_n(we_n), .data_mask_low(data_mask_low), .data_mask_high(data_mask_high)
);

endmodule

output_sdram_test.vcd
$date
	Sat Sep 28 19:24:56 2019
$end
$version
	Icarus Verilog
$end
$timescale
	1ps
$end
$scope module sdram_controller_tb $end
$var wire 12 ! addr [11:0] $end
$var wire 2 " bank_addr [1:0] $end
$var wire 1 # busy $end
$var wire 1 $ cas_n $end
$var wire 1 % clock_enable $end
$var wire 1 & cs_n $end
$var wire 16 ' data [15:0] $end
$var wire 1 ( data_mask_high $end
$var wire 1 ) data_mask_low $end
$var wire 16 * data_output [15:0] $end
$var wire 1 + ras_n $end
$var wire 1 , we_n $end
$var reg 1 - clk $end
$var reg 16 . data_input [15:0] $end
$var reg 16 / data_r [15:0] $end
$var reg 22 0 haddr [21:0] $end
$var reg 1 1 rd_enable $end
$var reg 1 2 rst_n $end
$var reg 1 3 wr_enable $end
$scope module sdram_controlleri $end
$var wire 12 4 addr [11:0] $end
$var wire 2 5 bank_addr [1:0] $end
$var wire 1 $ cas_n $end
$var wire 1 6 clk $end
$var wire 1 % clock_enable $end
$var wire 1 & cs_n $end
$var wire 16 7 data [15:0] $end
$var wire 1 ( data_mask_high $end
$var wire 1 ) data_mask_low $end
$var wire 1 + ras_n $end
$var wire 22 8 rd_addr [21:0] $end
$var wire 16 9 rd_data [15:0] $end
$var wire 1 : rd_enable $end
$var wire 1 ; rd_ready $end
$var wire 1 < rst_n $end
$var wire 1 , we_n $end
$var wire 22 = wr_addr [21:0] $end
$var wire 16 > wr_data [15:0] $end
$var wire 1 ? wr_enable $end
$var reg 12 @ addr_r [11:0] $end
$var reg 2 A bank_addr_r [1:0] $end
$var reg 1 B busy $end
$var reg 8 C command [7:0] $end
$var reg 8 D command_nxt [7:0] $end
$var reg 1 E data_mask_high_r $end
$var reg 1 F data_mask_low_r $end
$var reg 22 G haddr_r [21:0] $end
$var reg 5 H next [4:0] $end
$var reg 16 I rd_data_r [15:0] $end
$var reg 1 J rd_ready_r $end
$var reg 10 K refresh_cnt [9:0] $end
$var reg 5 L state [4:0] $end
$var reg 4 M state_cnt [3:0] $end
$var reg 4 N state_cnt_nxt [3:0] $end
$var reg 16 O wr_data_r [15:0] $end
$upscope $end
$upscope $end
$enddefinitions $end
#0
$dumpvars
bx O
b0 N
bx M
bx L
bx K
xJ
bx I
bx H
bx G
xF
xE
bx D
bx C
xB
bx A
bx @
0?
b0 >
b0 =
1<
x;
0:
bx 9
b0 8
bx 7
06
bx 5
bx 4
03
12
01
b0 0
bz /
b0 .
0-
x,
x+
bx *
x)
x(
bx '
x&
x%
x$
x#
bx "
bx !
$end
#1
0J
0;
1-
16
#2
0-
06
#3
1,
1$
1+
0&
1%
b0 !
b0 4
b0 "
b0 5
b1000 H
b10111000 D
b0 @
b0 A
1F
1)
1E
1(
bz '
bz 7
b0 K
0B
0#
b0 I
b0 *
b0 9
b0 O
b0 G
b1111 M
b10111000 C
b1000 L
1-
16
02
0<
#4
0-
06
#5
1-
16
#6
0-
06
12
1<
#7
b1 K
b1110 M
1-
16
#8
0-
06
#9
b1101 M
b10 K
1-
16
#10
0-
06
#11
b11 K
b1100 M
1-
16
#12
0-
06
#13
b1011 M
b100 K
1-
16
#14
0-
06
#15
b101 K
b1010 M
1-
16
#16
0-
06
#17
b1001 M
b110 K
1-
16
#18
0-
06
#19
b111 K
b1000 M
1-
16
#20
0-
06
#21
b111 M
b1000 K
1-
16
#22
0-
06
#23
b1001 K
b110 M
1-
16
#24
0-
06
#25
b101 M
b1010 K
1-
16
#26
0-
06
#27
b1011 K
b100 M
1-
16
#28
0-
06
#29
b11 M
b1100 K
1-
16
#30
0-
06
#31
b1101 K
b10 M
1-
16
#32
0-
06
#33
b1 M
b1110 K
1-
16
#34
0-
06
#35
b10010001 D
b1001 H
b1111 K
b0 M
1-
16
#36
0-
06
#37
0,
0+
b10000000000 !
b10000000000 4
b101 H
b10111000 D
b10010001 C
b1001 L
b10000 K
1-
16
#38
0-
06
#39
1,
1+
b0 !
b0 4
b10001000 D
b1010 H
b10001 K
b10111000 C
b101 L
1-
16
#40
0-
06
#41
0$
0+
b111 N
b1011 H
b10111000 D
b10001000 C
b1010 L
b10010 K
1-
16
#42
0-
06
#43
1$
1+
b0 N
b10011 K
b111 M
b10111000 C
b1011 L
1-
16
#44
0-
06
#45
b110 M
b10100 K
1-
16
#46
0-
06
#47
b10101 K
b101 M
1-
16
#48
0-
06
#49
b100 M
b10110 K
1-
16
#50
0-
06
#51
b10111 K
b11 M
1-
16
#52
0-
06
#53
b10 M
b11000 K
1-
16
#54
0-
06
#55
b11001 K
b1 M
1-
16
#56
0-
06
#57
b10001000 D
b1100 H
b0 M
b11010 K
1-
16
#58
0-
06
#59
0$
0+
b111 N
b1101 H
b10111000 D
b11011 K
b10001000 C
b1100 L
1-
16
#60
0-
06
#61
1$
1+
b0 N
b111 M
b10111000 C
b1101 L
b11100 K
1-
16
#62
0-
06
#63
b11101 K
b110 M
1-
16
#64
0-
06
#65
b101 M
b11110 K
1-
16
#66
0-
06
#67
b11111 K
b100 M
1-
16
#68
0-
06
#69
b11 M
b100000 K
1-
16
#70
0-
06
#71
b100001 K
b10 M
1-
16
#72
0-
06
#73
b1 M
b100010 K
1-
16
#74
0-
06
#75
b1000000x D
b1110 H
b100011 K
b0 M
1-
16
#76
0-
06
#77
0,
0$
0+
b1000110000 !
b1000110000 4
b1000110000 @
b1 N
b1111 H
b10111000 D
b1000000x C
b1110 L
b100100 K
1-
16
#78
0-
06
#79
1,
1$
1+
b0 !
b0 4
b0 N
b0 @
b100101 K
b1 M
b10111000 C
b1111 L
1-
16
#80
0-
06
#81
b0 H
b0 M
b100110 K
1-
16
#82
0-
06
#83
b100111 K
b0 L
1-
16
#84
0-
06
#85
b101000 K
1-
16
#86
0-
06
#87
b101001 K
1-
16
#88
0-
06
#89
b101010 K
1-
16
#90
0-
06
#91
b101011 K
1-
16
#92
0-
06
#93
b101100 K
1-
16
#94
0-
06
#95
b101101 K
1-
16
#96
0-
06
#97
b101110 K
1-
16
#98
0-
06
#99
b101111 K
1-
16
#100
0-
06
#101
b110000 K
1-
16
#102
0-
06
#103
b110001 K
1-
16
#104
0-
06
#105
b110010 K
1-
16
#106
0-
06
#107
b110011 K
1-
16
#108
0-
06
#109
b110100 K
1-
16
#110
0-
06
#111
b110101 K
1-
16
#112
0-
06
#113
b110110 K
1-
16
#114
0-
06
#115
b110111 K
1-
16
#116
0-
06
#117
b111000 K
1-
16
#118
0-
06
#119
b111001 K
1-
16
#120
0-
06
#121
b111010 K
1-
16
#122
0-
06
#123
b111011 K
1-
16
#124
0-
06
#125
b111100 K
1-
16
#126
0-
06
b110100000101 .
b110100000101 >
b1111101101101111101101 0
b1111101101101111101101 8
b1111101101101111101101 =
#127
b111101 K
1-
16
#128
0-
06
#129
0+
b111011011011 !
b111011011011 4
b11 "
b11 5
b111011011011 @
b11 A
0F
0)
0E
0(
b1 N
b1111101101101111101101 G
b110100000101 O
b10011xxx C
b11000 L
b111110 K
1-
16
b10111000 D
b11001 H
13
1?
#130
0-
06
#131
1+
b0 !
b0 4
b0 "
b0 5
b0 N
b0 @
b0 A
b111111 K
1B
1#
b1 M
b10111000 C
b11001 L
1-
16
#132
0-
06
#133
b10100xx1 D
b11010 H
b0 M
b1000000 K
1-
16
#134
0-
06
#135
0,
0$
b10011101101 !
b10011101101 4
b11 "
b11 5
b1 N
b11011 H
b10011101101 @
b11 A
b110100000101 '
b110100000101 7
b1000001 K
b10100xx1 C
b11010 L
1-
16
b10111000 D
b0 .
b0 >
b0 0
b0 8
b0 =
03
0?
#136
0-
06
#137
1,
1$
b0 !
b0 4
b0 "
b0 5
b0 @
b0 A
bz '
bz 7
b0 N
b1 M
b10111000 C
b11011 L
b1000010 K
1-
16
#138
0-
06
#139
b0 H
b1000011 K
b0 M
1-
16
#140
0-
06
#141
1F
1)
1E
1(
b0 L
b1000100 K
1-
16
#142
0-
06
#143
b1000101 K
0B
0#
1-
16
#144
0-
06
#145
b1000110 K
1-
16
#146
0-
06
#147
b1000111 K
1-
16
#148
0-
06
#149
b1001000 K
1-
16
#150
0-
06
#151
b1001001 K
1-
16
#152
0-
06
#153
b1001010 K
1-
16
#154
0-
06
#155
b1001011 K
1-
16
#156
0-
06
#157
b1001100 K
1-
16
#158
0-
06
#159
b1001101 K
1-
16
#160
0-
06
#161
b1001110 K
1-
16
#162
0-
06
#163
b1001111 K
1-
16
#164
0-
06
#165
b1010000 K
1-
16
#166
0-
06
#167
b1010001 K
1-
16
#168
0-
06
#169
b1010010 K
1-
16
#170
0-
06
#171
b1010011 K
1-
16
#172
0-
06
#173
b1010100 K
1-
16
#174
0-
06
#175
b1010101 K
1-
16
#176
0-
06
#177
b1010110 K
1-
16
#178
0-
06
#179
b1010111 K
1-
16
#180
0-
06
#181
b1011000 K
1-
16
#182
0-
06
#183
b1011001 K
1-
16
#184
0-
06
#185
b1011010 K
1-
16
#186
0-
06
#187
b1011011 K
1-
16
#188
0-
06
#189
b1011100 K
1-
16
#190
0-
06
#191
b1011101 K
1-
16
#192
0-
06
#193
b1011110 K
1-
16
#194
0-
06
#195
b1011111 K
1-
16
#196
0-
06
#197
b1100000 K
1-
16
#198
0-
06
#199
b1100001 K
1-
16
#200
0-
06
#201
b1100010 K
1-
16
#202
0-
06
#203
b1100011 K
1-
16
#204
0-
06
#205
b1100100 K
1-
16
#206
0-
06
#207
b1100101 K
1-
16
#208
0-
06
#209
b1100110 K
1-
16
#210
0-
06
#211
b1100111 K
1-
16
#212
0-
06
#213
b1101000 K
1-
16
#214
0-
06
#215
b1101001 K
1-
16
#216
0-
06
#217
b1101010 K
1-
16
#218
0-
06
#219
b1101011 K
1-
16
#220
0-
06
#221
b1101100 K
1-
16
#222
0-
06
#223
b1101101 K
1-
16
#224
0-
06
#225
b1101110 K
1-
16
#226
0-
06
#227
b1101111 K
1-
16
#228
0-
06
#229
b1110000 K
1-
16
#230
0-
06
#231
b1110001 K
1-
16
#232
0-
06
#233
b1110010 K
1-
16
#234
0-
06
#235
b1110011 K
1-
16
#236
0-
06
#237
b1110100 K
1-
16
#238
0-
06
#239
b1110101 K
1-
16
#240
0-
06
#241
b1110110 K
1-
16
#242
0-
06
#243
b1110111 K
1-
16
#244
0-
06
#245
b1111000 K
1-
16
#246
0-
06
#247
b1111001 K
1-
16
#248
0-
06
#249
b1111010 K
1-
16
#250
0-
06
#251
b1111011 K
1-
16
#252
0-
06
#253
b1111100 K
1-
16
#254
0-
06
#255
b1111101 K
1-
16
b1111101101111111101101 0
b1111101101111111101101 8
b1111101101111111101101 =
#256
0-
06
#257
b1111110 K
1-
16
#258
0-
06
b10011xxx D
b10000 H
11
1:
#259
0+
b111011011111 !
b111011011111 4
b11 "
b11 5
b1 N
b10001 H
b10111000 D
b111011011111 @
b11 A
0F
0)
0E
0(
b1111111 K
b1111101101111111101101 G
b10011xxx C
b10000 L
1-
16
#260
0-
06
#261
1+
b0 !
b0 4
b0 "
b0 5
b0 @
b0 A
b0 N
1B
1#
b1 M
b10111000 C
b10001 L
b10000000 K
1-
16
#262
0-
06
#263
b10101xx1 D
b10010 H
b10000001 K
b0 M
1-
16
#264
0-
06
b10101xx1 D
b0 0
b0 8
b0 =
01
0:
#265
0$
b10011101101 !
b10011101101 4
b11 "
b11 5
b10011101101 @
b11 A
b1 N
b10011 H
b10111000 D
b10101xx1 C
b10010 L
b10000010 K
1-
16
#266
0-
06
#267
1$
b0 !
b0 4
b0 "
b0 5
b0 N
b0 @
b0 A
b10000011 K
b1 M
b10111000 C
b10011 L
1-
16
#268
0-
06
#269
b10100 H
b0 M
b10000100 K
1-
16
#270
0-
06
#271
b0 H
b10000101 K
b10100 L
1-
16
#272
0-
06
b1011101110111011 /
b1011101110111011 '
b1011101110111011 7
#273
1F
1)
1E
1(
1J
1;
b1011101110111011 I
b1011101110111011 *
b1011101110111011 9
b0 L
b10000110 K
1-
16
#274
0-
06
bz /
bz '
bz 7
#275
b10000111 K
0B
0#
0J
0;
1-
16
#276
0-
06
#277
b10001000 K
1-
16
#278
0-
06
#279
b10001001 K
1-
16
#280
0-
06
#281
b10001010 K
1-
16
#282
0-
06
#283
b10001011 K
1-
16
#284
0-
06
#285
b10001100 K
1-
16
#286
0-
06
#287
b10001101 K
1-
16
#288
0-
06
#289
b10001110 K
1-
16
#290
0-
06
#291
b10001111 K
1-
16
#292
0-
06
#293
b10010000 K
1-
16
#294
0-
06
#295
b10010001 K
1-
16
#296
0-
06
#297
b10010010 K
1-
16
#298
0-
06
#299
b10010011 K
1-
16
#300
0-
06
#301
b10010100 K
1-
16
#302
0-
06
#303
b10010101 K
1-
16
#304
0-
06
#305
b10010110 K
1-
16
#306
0-
06
#307
b10010111 K
1-
16
#308
0-
06
#309
b10011000 K
1-
16
#310
0-
06
#311
b10011001 K
1-
16
#312
0-
06
#313
b10011010 K
1-
16
#314
0-
06
#315
b10011011 K
1-
16
#316
0-
06
#317
b10011100 K
1-
16
#318
0-
06
#319
b10011101 K
1-
16
#320
0-
06
#321
b10011110 K
1-
16
#322
0-
06
#323
b10011111 K
1-
16
#324
0-
06
#325
b10100000 K
1-
16
#326
0-
06
#327
b10100001 K
1-
16
#328
0-
06
#329
b10100010 K
1-
16
#330
0-
06
#331
b10100011 K
1-
16
#332
0-
06
#333
b10100100 K
1-
16
#334
0-
06
#335
b10100101 K
1-
16
#336
0-
06
#337
b10100110 K
1-
16
#338
0-
06
#339
b10100111 K
1-
16
#340
0-
06
#341
b10101000 K
1-
16
#342
0-
06
#343
b10101001 K
1-
16
#344
0-
06
#345
b10101010 K
1-
16
#346
0-
06
#347
b10101011 K
1-
16
#348
0-
06
#349
b10101100 K
1-
16
#350
0-
06
#351
b10101101 K
1-
16
#352
0-
06
#353
b10101110 K
1-
16
#354
0-
06
#355
b10101111 K
1-
16
#356
0-
06
#357
b10110000 K
1-
16
#358
0-
06
#359
b10110001 K
1-
16
#360
0-
06
#361
b10110010 K
1-
16
#362
0-
06
#363
b10110011 K
1-
16
#364
0-
06
#365
b10110100 K
1-
16
#366
0-
06
#367
b10110101 K
1-
16
#368
0-
06
#369
b10110110 K
1-
16
#370
0-
06
#371
b10110111 K
1-
16
#372
0-
06
#373
b10111000 K
1-
16
#374
0-
06
#375
b10111001 K
1-
16
#376
0-
06
#377
b10111010 K
1-
16
#378
0-
06
#379
b10111011 K
1-
16
#380
0-
06
#381
b10111100 K
1-
16
#382
0-
06
#383
b10111101 K
1-
16
#384
0-
06
#385
b10111110 K
1-
16
#386
0-
06
#387
b10111111 K
1-
16
#388
0-
06
#389
b11000000 K
1-
16
#390
0-
06
#391
b11000001 K
1-
16
#392
0-
06
#393
b11000010 K
1-
16
#394
0-
06
#395
b11000011 K
1-
16
#396
0-
06
#397
b11000100 K
1-
16
#398
0-
06
#399
b11000101 K
1-
16
#400
0-
06
#401
b11000110 K
1-
16
#402
0-
06
#403
b11000111 K
1-
16
#404
0-
06
#405
b11001000 K
1-
16
#406
0-
06
#407
b11001001 K
1-
16
#408
0-
06
#409
b11001010 K
1-
16
#410
0-
06
#411
b11001011 K
1-
16
#412
0-
06
#413
b11001100 K
1-
16
#414
0-
06
#415
b11001101 K
1-
16
#416
0-
06
#417
b11001110 K
1-
16
#418
0-
06
#419
b11001111 K
1-
16
#420
0-
06
#421
b11010000 K
1-
16
#422
0-
06
#423
b11010001 K
1-
16
#424
0-
06
#425
b11010010 K
1-
16
#426
0-
06
#427
b11010011 K
1-
16
#428
0-
06
#429
b11010100 K
1-
16
#430
0-
06
#431
b11010101 K
1-
16
#432
0-
06
#433
b11010110 K
1-
16
#434
0-
06
#435
b11010111 K
1-
16
#436
0-
06
#437
b11011000 K
1-
16
#438
0-
06
#439
b11011001 K
1-
16
#440
0-
06
#441
b11011010 K
1-
16
#442
0-
06
#443
b11011011 K
1-
16
#444
0-
06
#445
b11011100 K
1-
16
#446
0-
06
#447
b11011101 K
1-
16
#448
0-
06
#449
b11011110 K
1-
16
#450
0-
06
#451
b11011111 K
1-
16
#452
0-
06
#453
b11100000 K
1-
16
#454
0-
06
#455
b11100001 K
1-
16
#456
0-
06
#457
b11100010 K
1-
16
#458
0-
06
#459
b11100011 K
1-
16
#460
0-
06
#461
b11100100 K
1-
16
#462
0-
06
#463
b11100101 K
1-
16
#464
0-
06
#465
b11100110 K
1-
16
#466
0-
06
#467
b11100111 K
1-
16
#468
0-
06
#469
b11101000 K
1-
16
#470
0-
06
#471
b11101001 K
1-
16
#472
0-
06
#473
b11101010 K
1-
16
#474
0-
06
#475
b11101011 K
1-
16
#476
0-
06
#477
b11101100 K
1-
16
#478
0-
06
#479
b11101101 K
1-
16
#480
0-
06
#481
b11101110 K
1-
16
#482
0-
06
#483
b11101111 K
1-
16
#484
0-
06
#485
b11110000 K
1-
16
#486
0-
06
#487
b11110001 K
1-
16
#488
0-
06
#489
b11110010 K
1-
16
#490
0-
06
#491
b11110011 K
1-
16
#492
0-
06
#493
b11110100 K
1-
16
#494
0-
06
#495
b11110101 K
1-
16
#496
0-
06
#497
b11110110 K
1-
16
#498
0-
06
#499
b11110111 K
1-
16
#500
0-
06
#501
b11111000 K
1-
16
#502
0-
06
#503
b11111001 K
1-
16
#504
0-
06
#505
b11111010 K
1-
16
#506
0-
06
#507
b11111011 K
1-
16
#508
0-
06
#509
b11111100 K
1-
16
#510
0-
06
#511
b11111101 K
1-
16
#512
0-
06
#513
b11111110 K
1-
16
#514
0-
06
#515
b11111111 K
1-
16
#516
0-
06
#517
b100000000 K
1-
16
#518
0-
06
#519
b100000001 K
1-
16
#520
0-
06
#521
b100000010 K
1-
16
#522
0-
06
#523
b100000011 K
1-
16
#524
0-
06
#525
b100000100 K
1-
16
#526
0-
06
#527
b100000101 K
1-
16
#528
0-
06
#529
b100000110 K
1-
16
#530
0-
06
#531
b100000111 K
1-
16
#532
0-
06
#533
b100001000 K
1-
16
#534
0-
06
#535
b100001001 K
1-
16
#536
0-
06
#537
b100001010 K
1-
16
#538
0-
06
